setup.py
pictureframe/__init__.py
pictureframe/core.py
pictureframe.egg-info/PKG-INFO
pictureframe.egg-info/SOURCES.txt
pictureframe.egg-info/dependency_links.txt
pictureframe.egg-info/top_level.txt