Metadata-Version: 1.0
Name: pictureframe
Version: 0.1.0
Summary: Structured container for image data
Home-page: https://github.com/yotam/pictureframe
Author: Yotam Doron
Author-email: doron.yotam@googlemail.com
License: BSD
Platform: UNKNOWN
